{
    "active": "00001",
    "books": {
        "00001": {
            "descr": "Il 2023 ha segnato il 100° anniversario dalla fondazione del Liceo Classico. Questo libro ripercorre i personaggi e momenti salienti di una delle scuole storiche altoatesine",
            "img": "00001.png",
            "title": "Tanti Voci Una Storia"
        },
        "00002": {
            "descr": "b wedv eqv",
            "img": "00002.png",
            "title": "ciao geinis"
        },
        "00003": {
            "descr": "descrizione eeeee",
            "img": "00003.png",
            "title": "tolotol"
        },
        "00004": {
            "descr": "wow",
            "img": "00004.png",
            "title": "ciao"
        },
        "00005": {
            "descr": "b wedv eqv",
            "img": "s.png",
            "title": "libro"
        }
    }
}